pyRona/__init__.py
pyRona/argparser.py
pyRona/file_parser.py
pyRona/md_outlier_remover.py
pyRona/pyRona.py
pyRona/plotters/__init__.py
pyRona/plotters/general_plotter.py
pyRona-0.2.0.data/data/bin/Baypass_workflow.R
pyRona-0.2.0.dist-info/DESCRIPTION.rst
pyRona-0.2.0.dist-info/METADATA
pyRona-0.2.0.dist-info/RECORD
pyRona-0.2.0.dist-info/WHEEL
pyRona-0.2.0.dist-info/entry_points.txt
pyRona-0.2.0.dist-info/metadata.json
pyRona-0.2.0.dist-info/top_level.txt
