Metadata-Version: 2.0
Name: pyRona
Version: 0.2.0
Summary: A python implementation of "Risk of non Adaptedness"method (with a bit of R too!)
Home-page: https://github.com/StuntsPT/pyRona
Author: Francisco Pina-Martins
Author-email: f.pinamartins@gmail.com
License: GPL3
Download-URL: https://github.com/StuntsPT/pyRona/archive/v0.2.0.tar.gz
Platform: UNKNOWN
Classifier: Intended Audience :: Science/Research
Classifier: License :: OSI Approved :: GNU General Public License v3 (GPLv3)
Classifier: Natural Language :: English
Classifier: Operating System :: POSIX :: Linux
Classifier: Topic :: Scientific/Engineering :: Bio-Informatics
Classifier: Programming Language :: Python :: 3 :: Only
Classifier: Programming Language :: Python :: 3.4
Classifier: Programming Language :: Python :: 3.5
Classifier: Programming Language :: Python :: 3.6
Requires-Dist: matplotlib
Requires-Dist: numpy
